amigados/__init__.py
amigados/bumprev.py
amigados/fdtool.py
amigados/png2image.py
amigados_utils-0.1.1.data/scripts/amigados-bumprev
amigados_utils-0.1.1.data/scripts/amigados-copy
amigados_utils-0.1.1.data/scripts/amigados-createdisk
amigados_utils-0.1.1.data/scripts/amigados-dalf
amigados_utils-0.1.1.data/scripts/amigados-delete
amigados_utils-0.1.1.data/scripts/amigados-dir
amigados_utils-0.1.1.data/scripts/amigados-fdtool
amigados_utils-0.1.1.data/scripts/amigados-makedir
amigados_utils-0.1.1.data/scripts/amigados-png2image
amigados_utils-0.1.1.dist-info/LICENSE
amigados_utils-0.1.1.dist-info/METADATA
amigados_utils-0.1.1.dist-info/WHEEL
amigados_utils-0.1.1.dist-info/top_level.txt
amigados_utils-0.1.1.dist-info/RECORD
