Metadata-Version: 2.1
Name: amigados-utils
Version: 0.1.1
Summary: amigados-utils is a collection of utilities for Amiga system development
Home-page: https://github.com/weiju/amigados-utils
Author: Wei-ju Wu
Author-email: weiju.wu@gmail.com
Maintainer: Wei-ju Wu
Maintainer-email: weiju.wu@gmail.com
License: BSD
Keywords: amiga,system,development,classic,ecs,aga
Classifier: Development Status :: 4 - Beta
Classifier: Environment :: Console
Classifier: Intended Audience :: Developers
Classifier: Natural Language :: English
Classifier: License :: OSI Approved :: GNU General Public License v3 (GPLv3)
Classifier: Operating System :: OS Independent
Classifier: Programming Language :: Python
Classifier: Programming Language :: Python :: 3
Classifier: Programming Language :: Python :: Implementation :: CPython
Classifier: Topic :: Software Development :: Libraries :: Python Modules
License-File: LICENSE
Requires-Dist: pillow
Requires-Dist: Jinja2
